vasuki/__init__.py
vasuki/api.py
vasuki/cli.py
vasuki/core.py
vasuki/util.py
vasuki/format/__init__.py
vasuki/format/sixnibblename/LICENSE
vasuki/format/sixnibblename/README.md
vasuki/format/sixnibblename/__init__.py
vasuki/format/sixnibblename/sixnibblename.py
vasuki/random/__init__.py
vasuki/random/rwglc.py
vasuki/templates/index.html
vasuki/templates/vasuki.css
vasuki/unique/__init__.py
vasuki/unique/gibberish.py
vasuki/unique/moment.py
vasuki/unique/naga19.py
vasuki/unique/nagamani.py
vasuki/unique/ulid.py
vasuki/unique/uuid.py
vasuki-0.7.2.dist-info/licenses/LICENSE
vasuki-0.7.2.dist-info/METADATA
vasuki-0.7.2.dist-info/WHEEL
vasuki-0.7.2.dist-info/entry_points.txt
vasuki-0.7.2.dist-info/top_level.txt
vasuki-0.7.2.dist-info/RECORD
