Metadata-Version: 2.4
Name: vasuki
Version: 0.7.2
Summary: Vasuki generates different kinds of random unique identifiers, tokens, and words
Home-page: https://github.com/daq-tools/vasuki
Author: Andreas Motl
Author-email: andreas@terkin.org
License: MIT
Keywords: random unique identifier token word generator id uuid ulid hashid gibberish nagamani19
Classifier: Programming Language :: Python
Classifier: Programming Language :: Python :: 3.8
Classifier: Programming Language :: Python :: 3.9
Classifier: Programming Language :: Python :: 3.10
Classifier: Programming Language :: Python :: 3.11
Classifier: Programming Language :: Python :: 3.12
Classifier: Programming Language :: Python :: 3.13
Classifier: Programming Language :: Python :: 3.14
Classifier: License :: OSI Approved :: MIT License
Classifier: Development Status :: 4 - Beta
Classifier: Environment :: Console
Classifier: Environment :: Web Environment
Classifier: Intended Audience :: Developers
Classifier: Intended Audience :: Education
Classifier: Intended Audience :: Information Technology
Classifier: Intended Audience :: Manufacturing
Classifier: Intended Audience :: Science/Research
Classifier: Intended Audience :: System Administrators
Classifier: Intended Audience :: Telecommunications Industry
Classifier: Topic :: Communications
Classifier: Topic :: Database
Classifier: Topic :: Internet
Classifier: Topic :: Internet :: WWW/HTTP
Classifier: Topic :: Scientific/Engineering :: Human Machine Interfaces
Classifier: Topic :: Scientific/Engineering :: Information Analysis
Classifier: Topic :: Scientific/Engineering :: Interface Engine/Protocol Translator
Classifier: Topic :: Software Development :: Embedded Systems
Classifier: Topic :: Software Development :: Libraries
Classifier: Topic :: Software Development :: Object Brokering
Classifier: Topic :: System :: Archiving
Classifier: Topic :: System :: Networking :: Monitoring
Classifier: Topic :: Utilities
Classifier: Operating System :: POSIX
Classifier: Operating System :: Unix
Classifier: Operating System :: MacOS
License-File: LICENSE
Requires-Dist: docopt-ng<0.10
Requires-Dist: munch<5
Requires-Dist: ulid-py<1.2
Requires-Dist: hashids<1.4
Requires-Dist: gibberish<0.5
Provides-Extra: develop
Requires-Dist: build<2; extra == "develop"
Requires-Dist: bump2version==1.0.1; extra == "develop"
Requires-Dist: poethepoet<1; extra == "develop"
Requires-Dist: twine<7; extra == "develop"
Provides-Extra: service
Requires-Dist: responder>=3.0.0.dev0; extra == "service"
Provides-Extra: test
Requires-Dist: httpx<0.29; extra == "test"
Requires-Dist: pytest<10; extra == "test"
Requires-Dist: pytest-cov<8; extra == "test"
Dynamic: author
Dynamic: author-email
Dynamic: classifier
Dynamic: description
Dynamic: home-page
Dynamic: keywords
Dynamic: license
Dynamic: license-file
Dynamic: provides-extra
Dynamic: requires-dist
Dynamic: summary
